<?xml version="1.0" encoding="UTF-8"?>
<objects serializationModel="Studio.01.09.00">
    <object class="AudioFile" id="{607620dd-8cff-4cb9-81ea-43fb1831ce70}">
        <property name="assetPath">
            <value>Boss Tatu/tatuzao/tremechaoboostado.wav</value>
        </property>
        <property name="frequencyInKHz">
            <value>44.0999985</value>
        </property>
        <property name="channelCount">
            <value>1</value>
        </property>
        <property name="length">
            <value>5.1559863945578233</value>
        </property>
        <relationship name="masterAssetFolder">
            <destination>{6d4aace3-9861-4188-8c6b-f01f7f065ce6}</destination>
        </relationship>
    </object>
</objects>
