<?xml version="1.0" encoding="UTF-8"?>
<objects serializationModel="Studio.01.09.00">
    <object class="AudioFile" id="{915e08d5-2be7-4d49-a0d5-b79130bf06e1}">
        <property name="assetPath">
            <value>vomito4.wav</value>
        </property>
        <property name="frequencyInKHz">
            <value>44.0999985</value>
        </property>
        <property name="channelCount">
            <value>2</value>
        </property>
        <property name="length">
            <value>0.73024943310657597</value>
        </property>
        <relationship name="masterAssetFolder">
            <destination>{6d4aace3-9861-4188-8c6b-f01f7f065ce6}</destination>
        </relationship>
    </object>
</objects>
